traceloop/sdk/__init__.py
traceloop/sdk/config/__init__.py
traceloop/sdk/decorators/__init__.py
traceloop/sdk/fetcher.py
traceloop/sdk/prompts/__init__.py
traceloop/sdk/prompts/client.py
traceloop/sdk/prompts/model.py
traceloop/sdk/prompts/registry.py
traceloop/sdk/telemetry.py
traceloop/sdk/tracing/__init__.py
traceloop/sdk/tracing/content_allow_list.py
traceloop/sdk/tracing/context_manager.py
traceloop/sdk/tracing/tracing.py
traceloop/sdk/utils/__init__.py
traceloop/sdk/utils/in_memory_span_exporter.py
traceloop/sdk/version.py
vibranium_dome_openllmetry-0.3.6.dist-info/METADATA
vibranium_dome_openllmetry-0.3.6.dist-info/WHEEL
vibranium_dome_openllmetry-0.3.6.dist-info/RECORD
